reasonp/__init__.py
reasonp/insight.py
reasonp/main.py
reasonp/reason.py
reasonp/weight.py
reasonp-0.1.4.dist-info/LICENSE
reasonp-0.1.4.dist-info/METADATA
reasonp-0.1.4.dist-info/WHEEL
reasonp-0.1.4.dist-info/top_level.txt
reasonp-0.1.4.dist-info/RECORD
