Metadata-Version: 2.1
Name: reasonp
Version: 0.1.4
Summary: Data analysis tool for finding reasons for changes in data
Author: brendon.lin
Author-email: brendon.lin@outlook.com
License: UNKNOWN
Platform: UNKNOWN
License-File: LICENSE
Requires-Dist: pandas (>=1.1.0)
